login_harvest/__init__.py
login_harvest/analyzers.py
login_harvest/extractor.py
login_harvest/oauth_providers.json
tests/test_html_extractor.py
login_harvest-0.0.1a4.dist-info/METADATA
login_harvest-0.0.1a4.dist-info/WHEEL
login_harvest-0.0.1a4.dist-info/top_level.txt
login_harvest-0.0.1a4.dist-info/RECORD
