Metadata-Version: 2.1
Name: login-harvest
Version: 0.0.1a4
Summary: A library to extract login-related HTML elements from web pages.
Author-email: Victor DeLaplaine <auth.sentry@gmail.com>
Classifier: Programming Language :: Python :: 3
Classifier: Operating System :: OS Independent
Requires-Python: >=3.12
Requires-Dist: beautifulsoup4
